algo_profiler/__init__.py
algo_profiler/big_o_analyzer.py
algo_profiler/big_o_complexities.py
algo_profiler/coverage_check.py
algo_profiler/helpers.py
algo_profiler/linear_space.py
algo_profiler/memory_check.py
algo_profiler/printers.py
algo_profiler/profiler.py
algo_profiler/profiling_by_line.py
algo_profiler/scalene_analyzer.py
algo_profiler/schema_check.py
algo_profiler/snakeviz_cli.py
algo_profiler/tester.py
algo_profiler/timer.py
algo_profiler/temp_files/.gitkeep
algo_profiler-0.0.24.dist-info/LICENSE
algo_profiler-0.0.24.dist-info/METADATA
algo_profiler-0.0.24.dist-info/WHEEL
algo_profiler-0.0.24.dist-info/top_level.txt
algo_profiler-0.0.24.dist-info/RECORD
